shigma/__init__.py
shigma/shigma.py
shigma-0.0.1.dist-info/LICENSE
shigma-0.0.1.dist-info/METADATA
shigma-0.0.1.dist-info/WHEEL
shigma-0.0.1.dist-info/top_level.txt
shigma-0.0.1.dist-info/RECORD
