Metadata-Version: 2.1
Name: shigma
Version: 0.0.1
Summary: Allows for doing mathematical sigma and pi notation.
Home-page: https://github.com/lekritz/shigma
Author: Lekritz (Henryk Popioɫek)
License: M.I.T. License
Keywords: python,sigma,pi,maths,math,mathematics
Classifier: Development Status :: 2 - Pre-Alpha
Classifier: Intended Audience :: Other Audience
Classifier: Programming Language :: Python :: 3
Classifier: License :: OSI Approved :: MIT License
Classifier: Operating System :: Unix
Classifier: Operating System :: MacOS :: MacOS X
Classifier: Operating System :: Microsoft :: Windows
Requires-Python: >=3.0
License-File: LICENSE
Provides-Extra: dev
Requires-Dist: pytest >=7.0 ; extra == 'dev'
Requires-Dist: twine >=4.0.2 ; extra == 'dev'
